plutis_cli/__init__.py
plutis_cli/main.py
plutis_cli-0.1.5.dist-info/METADATA
plutis_cli-0.1.5.dist-info/WHEEL
plutis_cli-0.1.5.dist-info/entry_points.txt
plutis_cli-0.1.5.dist-info/top_level.txt
plutis_cli-0.1.5.dist-info/RECORD
