Metadata-Version: 2.1
Name: plutis-cli
Version: 0.1.5
Requires-Dist: PyYAML
Requires-Dist: requests
